[
    {
        "name": "Player Spawn",
        "type": "spawnPoint",
        "position": [
            32,
            36
        ]
    },
    {
        "name": "Slime",
        "type": "enemy",
        "image": "slime.png",
        "position": [
            41,
            37
        ],
        "enemyType": ["Slime", "Slime"],
        "level": [100, 100]
    },
    {
        "name": "NPC",
        "type": "npc",
        "NPCID": "Trapped_NPC",
        "position": [
            36,
            39
        ]
    }
]